SUMADOR_1_Y_4_BITS/Sumador_1bit/suma_1bit.v
module suma_1bit (
    input A, B, Ci,
    output Co, So
);

wire XOR_AB, AND_AB, AND_XOR_AB_Ci;

assign XOR_AB = A ^ B;
assign AND_AB = A & B;
assign So = XOR_AB ^ Ci;
assign AND_XOR_AB_Ci = XOR_AB & Ci;
assign Co = AND_XOR_AB_Ci | AND_AB;

//wire x_ab, cout_t, a_ab;

//xor(x_ab, A, B);
//xor(So, x_ab, Ci);
//and(cout_t, x_ab, Ci);
//and(a_ab, A, B);
//or(Co, cout_t, a_ab);

//reg [1:0] sum_all;

//always @(*) begin
  //  sum_all = A + B + Ci;  
//end

//assign Co = sum_all[1];
//assign So = sum_all[0];

endmodule

SUMADOR_1_Y_4_BITS/Sumador_1bit/suma_1bit_tb.v
`timescale 1ns / 1ps
`include "Sumador_1bit/suma_1bit.v"

module suma_1bit_tb;
    // Declaración de señales
    reg A, B, Ci;
    wire Co, So;
    
    // Instanciación del módulo bajo prueba
    suma_1bit uut (
        .A(A),
        .B(B),
        .Ci(Ci),
        .Co(Co),
        .So(So)
    );
    
    // Generación de estímulos
    initial begin
        // Inicializar entradas
        A = 0;
        B = 0;
        Ci = 0;
        
        #10 A = 0; B = 0; Ci = 0;
        #10 A = 0; B = 0; Ci = 1;
        #10 A = 0; B = 1; Ci = 0;
        #10 A = 0; B = 1; Ci = 1;
        #10 A = 1; B = 0; Ci = 0;
        #10 A = 1; B = 0; Ci = 1;
        #10 A = 1; B = 1; Ci = 0;
        #10 A = 1; B = 1; Ci = 1;
        
        // Finalizar simulación
        #10 $finish;
    end
    
    initial begin
        $dumpfile("suma_1bit_tb.vcd");
        $dumpvars(0, suma_1bit_tb);
    end
endmodule

SUMADOR_1_Y_4_BITS/suma_1bit_tb.vcd
$date
	Fri Sep 05 22:15:02 2025
$end
$version
	Icarus Verilog
$end
$timescale
	1ps
$end
$scope module suma_1bit_tb $end
$var wire 1 ! So $end
$var wire 1 " Co $end
$var reg 1 # A $end
$var reg 1 $ B $end
$var reg 1 % Ci $end
$scope module uut $end
$var wire 1 # A $end
$var wire 1 & AND_AB $end
$var wire 1 ' AND_XOR_AB_Ci $end
$var wire 1 $ B $end
$var wire 1 % Ci $end
$var wire 1 " Co $end
$var wire 1 ! So $end
$var wire 1 ( XOR_AB $end
$upscope $end
$upscope $end
$enddefinitions $end
$comment Show the parameter values. $end
$dumpall
$end
#0
$dumpvars
0(
0'
0&
0%
0$
0#
0"
0!
$end
#20000
1!
1%
#30000
1(
0%
1$
#40000
1"
0!
1'
1%
#50000
0"
1!
0'
0%
0$
1#
#60000
1"
0!
1'
1%
#70000
0'
0(
1&
0%
1$
#80000
1!
1%
