SUMADOR_1_Y_4_BITS/Sumador_4bit/suma_1bit2.v
module suma_1bit2 (
    input A, B, Ci,
    output Co, So

);

wire XOR_AB, AND_AB, AND_XOR_AB_Ci;

assign XOR_AB = A ^ B;
assign AND_AB = A & B;
assign So = XOR_AB ^ Ci;
assign AND_XOR_AB_Ci = XOR_AB & Ci;
assign Co = AND_XOR_AB_Ci | AND_AB;

endmodule

lab01-sumador-1-y-4-bits-2025-ii-ap-g1-e04/Sumador_4bit/suma_4bit.v
module suma_4bit (
    input  [3:0] A,
    input  [3:0] B,
    input        Ci,
    output [3:0] S,
    output       Co
);

wire c1, c2, c3;

 // Instanciación de 4 sumadores de 1 bit
    suma_1bit2 FA0 (.A(A[0]), .B(B[0]), .Ci(Ci),  .So(S[0]), .Co(c1));
    suma_1bit2 FA1 (.A(A[1]), .B(B[1]), .Ci(c1),  .So(S[1]), .Co(c2));
    suma_1bit2 FA2 (.A(A[2]), .B(B[2]), .Ci(c2),  .So(S[2]), .Co(c3));
    suma_1bit2 FA3 (.A(A[3]), .B(B[3]), .Ci(c3),  .So(S[3]), .Co(Co));

endmodule

SUMADOR_1_Y_4_BITS/Sumador_4bit/suma_4bit_tb.v
`timescale 1ns / 1ps
`include "Sumador_4bit/suma_4bit.v"
`include "Sumador_4bit/suma_1bit2.v"

module suma_4bit_tb;

    // Entradas
    reg [3:0] A_tb;
    reg [3:0] B_tb;
    reg Ci_tb;
    // Salidas
    wire [3:0] So_tb;
    wire Co_tb;

    // Instancia del módulo bajo prueba
    suma_4bit uut (
        .A(A_tb),
        .B(B_tb),
        .Ci(Ci_tb),
        .S(So_tb),
        .Co(Co_tb)
    );

     initial begin
        A_tb   = 4'd0;
        B_tb   = 4'd0; 
        Ci_tb = 1'd0;

        for (B_tb = 0; B_tb < 15; B_tb = B_tb + 1) begin
            #10;
        end

        B_tb = 4'd15;
        #10;

        for (B_tb = 0; B_tb < 16; B_tb = B_tb + 1) begin
            if (B_tb == 0) begin
                A_tb = A_tb + 1;
            end
            #10;
        end
    end
    
    initial begin
        $dumpfile("suma_4bit_tb.vcd");
        $dumpvars(-1, suma_4bit_tb);

         #2500 $finish;  
    end

endmodule

lab01-sumador-1-y-4-bits-2025-ii-ap-g1-e04/suma_4bit_tb.vcd
$date
	Sat Sep 06 17:48:32 2025
$end
$version
	Icarus Verilog
$end
$timescale
	1ps
$end
$scope module suma_4bit_tb $end
$var wire 4 ! So_tb [3:0] $end
$var wire 1 " Co_tb $end
$var reg 4 # A_tb [3:0] $end
$var reg 4 $ B_tb [3:0] $end
$var reg 1 % Ci_tb $end
$scope module uut $end
$var wire 4 & A [3:0] $end
$var wire 4 ' B [3:0] $end
$var wire 1 % Ci $end
$var wire 1 ( c3 $end
$var wire 1 ) c2 $end
$var wire 1 * c1 $end
$var wire 4 + S [3:0] $end
$var wire 1 " Co $end
$scope module FA0 $end
$var wire 1 , A $end
$var wire 1 - AND_AB $end
$var wire 1 . AND_XOR_AB_Ci $end
$var wire 1 / B $end
$var wire 1 % Ci $end
$var wire 1 * Co $end
$var wire 1 0 So $end
$var wire 1 1 XOR_AB $end
$upscope $end
$scope module FA1 $end
$var wire 1 2 A $end
$var wire 1 3 AND_AB $end
$var wire 1 4 AND_XOR_AB_Ci $end
$var wire 1 5 B $end
$var wire 1 * Ci $end
$var wire 1 ) Co $end
$var wire 1 6 So $end
$var wire 1 7 XOR_AB $end
$upscope $end
$scope module FA2 $end
$var wire 1 8 A $end
$var wire 1 9 AND_AB $end
$var wire 1 : AND_XOR_AB_Ci $end
$var wire 1 ; B $end
$var wire 1 ) Ci $end
$var wire 1 ( Co $end
$var wire 1 < So $end
$var wire 1 = XOR_AB $end
$upscope $end
$scope module FA3 $end
$var wire 1 > A $end
$var wire 1 ? AND_AB $end
$var wire 1 @ AND_XOR_AB_Ci $end
$var wire 1 A B $end
$var wire 1 ( Ci $end
$var wire 1 " Co $end
$var wire 1 B So $end
$var wire 1 C XOR_AB $end
$upscope $end
$upscope $end
$upscope $end
$enddefinitions $end
$comment Show the parameter values. $end
$dumpall
$end
#0
$dumpvars
0C
0B
0A
0@
0?
0>
0=
0<
0;
0:
09
08
07
06
05
04
03
02
01
00
0/
0.
0-
0,
b0 +
0*
0)
0(
b0 '
b0 &
0%
b0 $
b0 #
0"
b0 !
$end
#10000
b1 !
b1 +
10
11
1/
b1 $
b1 '
#20000
00
b10 !
b10 +
16
01
17
0/
15
b10 $
b10 '
#30000
b11 !
b11 +
10
11
1/
b11 $
b11 '
#40000
00
06
b100 !
b100 +
1<
01
07
1=
0/
05
1;
b100 $
b100 '
#50000
b101 !
b101 +
10
11
1/
b101 $
b101 '
#60000
00
b110 !
b110 +
16
01
17
0/
15
b110 $
b110 '
#70000
b111 !
b111 +
10
11
1/
b111 $
b111 '
#80000
00
06
0<
b1000 !
b1000 +
1B
01
07
0=
1C
0/
05
0;
1A
b1000 $
b1000 '
#90000
b1001 !
b1001 +
10
11
1/
b1001 $
b1001 '
#100000
00
b1010 !
b1010 +
16
01
17
0/
15
b1010 $
b1010 '
#110000
b1011 !
b1011 +
10
11
1/
b1011 $
b1011 '
#120000
00
06
b1100 !
b1100 +
1<
01
07
1=
0/
05
1;
b1100 $
b1100 '
#130000
b1101 !
b1101 +
10
11
1/
b1101 $
b1101 '
#140000
00
b1110 !
b1110 +
16
01
17
0/
15
b1110 $
b1110 '
#150000
b1111 !
b1111 +
10
11
1/
b1111 $
b1111 '
#160000
06
0<
b1 !
b1 +
0B
07
0=
0C
1,
0/
05
0;
0A
b1 #
b1 &
b0 $
b0 '
#170000
16
b10 !
b10 +
00
1*
01
1-
1/
b1 $
b1 '
#180000
0<
0)
10
0*
b11 !
b11 +
16
04
11
0-
17
0/
15
b10 $
b10 '
#190000
1<
1)
06
14
b100 !
b100 +
00
1*
01
1-
1/
b11 $
b11 '
#200000
0B
0)
0(
10
0*
06
04
b101 !
b101 +
1<
0:
11
0-
07
1=
0/
05
1;
b100 $
b100 '
#210000
16
b110 !
b110 +
00
1*
01
1-
1/
b101 $
b101 '
#220000
0B
0(
1<
0:
0)
10
0*
b111 !
b111 +
16
04
11
0-
17
0/
15
b110 $
b110 '
#230000
1B
1(
0<
1:
1)
06
14
b1000 !
b1000 +
00
1*
01
1-
1/
b111 $
b111 '
#240000
0)
0(
0"
10
0*
06
04
0<
0:
b1001 !
b1001 +
1B
0@
11
0-
07
0=
1C
0/
05
0;
1A
b1000 $
b1000 '
#250000
16
b1010 !
b1010 +
00
1*
01
1-
1/
b1001 $
b1001 '
#260000
0<
0)
10
0*
b1011 !
b1011 +
16
04
11
0-
17
0/
15
b1010 $
b1010 '
#270000
1<
1)
06
14
b1100 !
b1100 +
00
1*
01
1-
1/
b1011 $
b1011 '
#280000
0"
1B
0@
0)
0(
10
0*
06
04
b1101 !
b1101 +
1<
0:
11
0-
07
1=
0/
05
1;
b1100 $
b1100 '
#290000
16
b1110 !
b1110 +
00
1*
01
1-
1/
b1101 $
b1101 '
#300000
0"
1B
0@
0(
1<
0:
0)
10
0*
b1111 !
b1111 +
16
04
11
0-
17
0/
15
b1110 $
b1110 '
#310000
1"
0B
1@
1(
0<
1:
1)
06
14
b0 !
b0 +
00
1*
01
1-
1/
b1111 $
b1111 '
#320000
0)
16
04
0(
0"
0*
0<
0:
b10 !
b10 +
0B
0@
0-
0=
0C
0,
12
0/
05
0;
0A
b10 #
b10 &
b0 $
b0 '
#330000
b11 !
b11 +
10
11
1/
b1 $
b1 '
#340000
1<
00
b100 !
b100 +
06
1)
01
07
13
0/
15
b10 $
b10 '
#350000
b101 !
b101 +
10
11
1/
b11 $
b11 '
#360000
0B
0(
00
16
0)
b110 !
b110 +
1<
0:
01
17
03
1=
0/
05
1;
b100 $
b100 '
#370000
b111 !
b111 +
10
11
1/
b101 $
b101 '
#380000
1B
1(
0<
1:
00
b1000 !
b1000 +
06
1)
01
07
13
0/
15
b110 $
b110 '
#390000
b1001 !
b1001 +
10
11
1/
b111 $
b111 '
#400000
0(
0"
00
16
0)
0<
0:
b1010 !
b1010 +
1B
0@
01
17
03
0=
1C
0/
05
0;
1A
b1000 $
b1000 '
#410000
b1011 !
b1011 +
10
11
1/
b1001 $
b1001 '
#420000
1<
00
b1100 !
b1100 +
06
1)
01
07
13
0/
15
b1010 $
b1010 '
#430000
b1101 !
b1101 +
10
11
1/
b1011 $
b1011 '
#440000
0"
1B
0@
0(
00
16
0)
b1110 !
b1110 +
1<
0:
01
17
03
1=
0/
05
1;
b1100 $
b1100 '
#450000
b1111 !
b1111 +
10
11
1/
b1101 $
b1101 '
#460000
1"
0B
1@
1(
0<
1:
00
b0 !
b0 +
06
1)
01
07
13
0/
15
b1110 $
b1110 '
#470000
b1 !
b1 +
10
11
1/
b1111 $
b1111 '
#480000
0(
0"
16
0)
0<
0:
b11 !
b11 +
0B
0@
17
03
0=
0C
1,
0/
05
0;
0A
b11 #
b11 &
b0 $
b0 '
#490000
1<
1)
06
14
b100 !
b100 +
00
1*
01
1-
1/
b1 $
b1 '
#500000
10
0*
b101 !
b101 +
06
04
11
0-
07
13
0/
15
b10 $
b10 '
#510000
16
b110 !
b110 +
00
1*
01
1-
1/
b11 $
b11 '
#520000
0B
0(
10
0*
16
04
0)
b111 !
b111 +
1<
0:
11
0-
17
03
1=
0/
05
1;
b100 $
b100 '
#530000
1B
1(
0<
1:
1)
06
14
b1000 !
b1000 +
00
1*
01
1-
1/
b101 $
b101 '
#540000
10
0*
b1001 !
b1001 +
06
04
11
0-
07
13
0/
15
b110 $
b110 '
#550000
16
b1010 !
b1010 +
00
1*
01
1-
1/
b111 $
b111 '
#560000
0(
0"
10
0*
16
04
0)
0<
0:
b1011 !
b1011 +
1B
0@
11
0-
17
03
0=
1C
0/
05
0;
1A
b1000 $
b1000 '
#570000
1<
1)
06
14
b1100 !
b1100 +
00
1*
01
1-
1/
b1001 $
b1001 '
#580000
10
0*
b1101 !
b1101 +
06
04
11
0-
07
13
0/
15
b1010 $
b1010 '
#590000
16
b1110 !
b1110 +
00
1*
01
1-
1/
b1011 $
b1011 '
#600000
0"
1B
0@
0(
10
0*
16
04
0)
b1111 !
b1111 +
1<
0:
11
0-
17
03
1=
0/
05
1;
b1100 $
b1100 '
#610000
1"
0B
1@
1(
0<
1:
1)
06
14
b0 !
b0 +
00
1*
01
1-
1/
b1101 $
b1101 '
#620000
10
0*
b1 !
b1 +
06
04
11
0-
07
13
0/
15
b1110 $
b1110 '
#630000
16
b10 !
b10 +
00
1*
01
1-
1/
b1111 $
b1111 '
#640000
0(
06
1<
0:
0"
0*
0)
b100 !
b100 +
0B
0@
0-
03
0C
0,
02
18
0/
05
0;
0A
b100 #
b100 &
b0 $
b0 '
#650000
b101 !
b101 +
10
11
1/
b1 $
b1 '
#660000
00
b110 !
b110 +
16
01
17
0/
15
b10 $
b10 '
#670000
b111 !
b111 +
10
11
1/
b11 $
b11 '
#680000
1B
00
06
b1000 !
b1000 +
0<
1(
01
07
0=
19
0/
05
1;
b100 $
b100 '
#690000
b1001 !
b1001 +
10
11
1/
b101 $
b101 '
#700000
00
b1010 !
b1010 +
16
01
17
0/
15
b110 $
b110 '
#710000
b1011 !
b1011 +
10
11
1/
b111 $
b111 '
#720000
0"
00
06
1<
0(
b1100 !
b1100 +
1B
0@
01
07
1=
09
1C
0/
05
0;
1A
b1000 $
b1000 '
#730000
b1101 !
b1101 +
10
11
1/
b1001 $
b1001 '
#740000
00
b1110 !
b1110 +
16
01
17
0/
15
b1010 $
b1010 '
#750000
b1111 !
b1111 +
10
11
1/
b1011 $
b1011 '
#760000
1"
0B
1@
00
06
b0 !
b0 +
0<
1(
01
07
0=
19
0/
05
1;
b1100 $
b1100 '
#770000
b1 !
b1 +
10
11
1/
b1101 $
b1101 '
#780000
00
b10 !
b10 +
16
01
17
0/
15
b1110 $
b1110 '
#790000
b11 !
b11 +
10
11
1/
b1111 $
b1111 '
#800000
0"
06
1<
0(
b101 !
b101 +
0B
0@
07
1=
09
0C
1,
0/
05
0;
0A
b101 #
b101 &
b0 $
b0 '
#810000
16
b110 !
b110 +
00
1*
01
1-
1/
b1 $
b1 '
#820000
0B
0(
1<
0:
0)
10
0*
b111 !
b111 +
16
04
11
0-
17
0/
15
b10 $
b10 '
#830000
1B
1(
0<
1:
1)
06
14
b1000 !
b1000 +
00
1*
01
1-
1/
b11 $
b11 '
#840000
0)
10
0*
06
04
b1001 !
b1001 +
0<
0:
11
0-
07
0=
19
0/
05
1;
b100 $
b100 '
#850000
16
b1010 !
b1010 +
00
1*
01
1-
1/
b101 $
b101 '
#860000
0<
0)
10
0*
b1011 !
b1011 +
16
04
11
0-
17
0/
15
b110 $
b110 '
#870000
1<
1)
06
14
b1100 !
b1100 +
00
1*
01
1-
1/
b111 $
b111 '
#880000
0)
0"
10
0*
06
04
1<
0:
0(
b1101 !
b1101 +
1B
0@
11
0-
07
1=
09
1C
0/
05
0;
1A
b1000 $
b1000 '
#890000
16
b1110 !
b1110 +
00
1*
01
1-
1/
b1001 $
b1001 '
#900000
0"
1B
0@
0(
1<
0:
0)
10
0*
b1111 !
b1111 +
16
04
11
0-
17
0/
15
b1010 $
b1010 '
#910000
1"
0B
1@
1(
0<
1:
1)
06
14
b0 !
b0 +
00
1*
01
1-
1/
b1011 $
b1011 '
#920000
0)
10
0*
06
04
b1 !
b1 +
0<
0:
11
0-
07
0=
19
0/
05
1;
b1100 $
b1100 '
#930000
16
b10 !
b10 +
00
1*
01
1-
1/
b1101 $
b1101 '
#940000
0<
0)
10
0*
b11 !
b11 +
16
04
11
0-
17
0/
15
b1110 $
b1110 '
#950000
1<
1)
06
14
b100 !
b100 +
00
1*
01
1-
1/
b1111 $
b1111 '
#960000
0)
16
04
0"
0*
1<
0:
0(
b110 !
b110 +
0B
0@
0-
1=
09
0C
0,
12
0/
05
0;
0A
b110 #
b110 &
b0 $
b0 '
#970000
b111 !
b111 +
10
11
1/
b1 $
b1 '
#980000
1B
1(
0<
1:
00
b1000 !
b1000 +
06
1)
01
07
13
0/
15
b10 $
b10 '
#990000
b1001 !
b1001 +
10
11
1/
b11 $
b11 '
#1000000
00
16
0)
b1010 !
b1010 +
0<
0:
01
17
03
0=
19
0/
05
1;
b100 $
b100 '
#1010000
b1011 !
b1011 +
10
11
1/
b101 $
b101 '
#1020000
1<
00
b1100 !
b1100 +
06
1)
01
07
13
0/
15
b110 $
b110 '
#1030000
b1101 !
b1101 +
10
11
1/
b111 $
b111 '
#1040000
0"
00
16
0)
1<
0:
0(
b1110 !
b1110 +
1B
0@
01
17
03
1=
09
1C
0/
05
0;
1A
b1000 $
b1000 '
#1050000
b1111 !
b1111 +
10
11
1/
b1001 $
b1001 '
#1060000
1"
0B
1@
1(
0<
1:
00
b0 !
b0 +
06
1)
01
07
13
0/
15
b1010 $
b1010 '
#1070000
b1 !
b1 +
10
11
1/
b1011 $
b1011 '
#1080000
00
16
0)
b10 !
b10 +
0<
0:
01
17
03
0=
19
0/
05
1;
b1100 $
b1100 '
#1090000
b11 !
b11 +
10
11
1/
b1101 $
b1101 '
#1100000
1<
00
b100 !
b100 +
06
1)
01
07
13
0/
15
b1110 $
b1110 '
#1110000
b101 !
b101 +
10
11
1/
b1111 $
b1111 '
#1120000
0"
16
0)
1<
0:
0(
b111 !
b111 +
0B
0@
17
03
1=
09
0C
1,
0/
05
0;
0A
b111 #
b111 &
b0 $
b0 '
#1130000
1B
1(
0<
1:
1)
06
14
b1000 !
b1000 +
00
1*
01
1-
1/
b1 $
b1 '
#1140000
10
0*
b1001 !
b1001 +
06
04
11
0-
07
13
0/
15
b10 $
b10 '
#1150000
16
b1010 !
b1010 +
00
1*
01
1-
1/
b11 $
b11 '
#1160000
10
0*
16
04
0)
b1011 !
b1011 +
0<
0:
11
0-
17
03
0=
19
0/
05
1;
b100 $
b100 '
#1170000
1<
1)
06
14
b1100 !
b1100 +
00
1*
01
1-
1/
b101 $
b101 '
#1180000
10
0*
b1101 !
b1101 +
06
04
11
0-
07
13
0/
15
b110 $
b110 '
#1190000
16
b1110 !
b1110 +
00
1*
01
1-
1/
b111 $
b111 '
#1200000
0"
10
0*
16
04
0)
1<
0:
0(
b1111 !
b1111 +
1B
0@
11
0-
17
03
1=
09
1C
0/
05
0;
1A
b1000 $
b1000 '
#1210000
1"
0B
1@
1(
0<
1:
1)
06
14
b0 !
b0 +
00
1*
01
1-
1/
b1001 $
b1001 '
#1220000
10
0*
b1 !
b1 +
06
04
11
0-
07
13
0/
15
b1010 $
b1010 '
#1230000
16
b10 !
b10 +
00
1*
01
1-
1/
b1011 $
b1011 '
#1240000
10
0*
16
04
0)
b11 !
b11 +
0<
0:
11
0-
17
03
0=
19
0/
05
1;
b1100 $
b1100 '
#1250000
1<
1)
06
14
b100 !
b100 +
00
1*
01
1-
1/
b1101 $
b1101 '
#1260000
10
0*
b101 !
b101 +
06
04
11
0-
07
13
0/
15
b1110 $
b1110 '
#1270000
16
b110 !
b110 +
00
1*
01
1-
1/
b1111 $
b1111 '
#1280000
0"
06
0<
b1000 !
b1000 +
1B
0@
0*
0)
0(
0-
03
09
0,
02
08
1>
0/
05
0;
0A
b1000 #
b1000 &
b0 $
b0 '
#1290000
b1001 !
b1001 +
10
11
1/
b1 $
b1 '
#1300000
00
b1010 !
b1010 +
16
01
17
0/
15
b10 $
b10 '
#1310000
b1011 !
b1011 +
10
11
1/
b11 $
b11 '
#1320000
00
06
b1100 !
b1100 +
1<
01
07
1=
0/
05
1;
b100 $
b100 '
#1330000
b1101 !
b1101 +
10
11
1/
b101 $
b101 '
#1340000
00
b1110 !
b1110 +
16
01
17
0/
15
b110 $
b110 '
#1350000
b1111 !
b1111 +
10
11
1/
b111 $
b111 '
#1360000
00
06
0<
b0 !
b0 +
0B
1"
01
07
0=
0C
1?
0/
05
0;
1A
b1000 $
b1000 '
#1370000
b1 !
b1 +
10
11
1/
b1001 $
b1001 '
#1380000
00
b10 !
b10 +
16
01
17
0/
15
b1010 $
b1010 '
#1390000
b11 !
b11 +
10
11
1/
b1011 $
b1011 '
#1400000
00
06
b100 !
b100 +
1<
01
07
1=
0/
05
1;
b1100 $
b1100 '
#1410000
b101 !
b101 +
10
11
1/
b1101 $
b1101 '
#1420000
00
b110 !
b110 +
16
01
17
0/
15
b1110 $
b1110 '
#1430000
b111 !
b111 +
10
11
1/
b1111 $
b1111 '
#1440000
06
0<
b1001 !
b1001 +
1B
0"
07
0=
1C
0?
1,
0/
05
0;
0A
b1001 #
b1001 &
b0 $
b0 '
#1450000
16
b1010 !
b1010 +
00
1*
01
1-
1/
b1 $
b1 '
#1460000
0<
0)
10
0*
b1011 !
b1011 +
16
04
11
0-
17
0/
15
b10 $
b10 '
#1470000
1<
1)
06
14
b1100 !
b1100 +
00
1*
01
1-
1/
b11 $
b11 '
#1480000
0"
1B
0@
0)
0(
10
0*
06
04
b1101 !
b1101 +
1<
0:
11
0-
07
1=
0/
05
1;
b100 $
b100 '
#1490000
16
b1110 !
b1110 +
00
1*
01
1-
1/
b101 $
b101 '
#1500000
0"
1B
0@
0(
1<
0:
0)
10
0*
b1111 !
b1111 +
16
04
11
0-
17
0/
15
b110 $
b110 '
#1510000
1"
0B
1@
1(
0<
1:
1)
06
14
b0 !
b0 +
00
1*
01
1-
1/
b111 $
b111 '
#1520000
0)
0(
10
0*
06
04
0<
0:
b1 !
b1 +
0B
0@
11
0-
07
0=
0C
1?
0/
05
0;
1A
b1000 $
b1000 '
#1530000
16
b10 !
b10 +
00
1*
01
1-
1/
b1001 $
b1001 '
#1540000
0<
0)
10
0*
b11 !
b11 +
16
04
11
0-
17
0/
15
b1010 $
b1010 '
#1550000
1<
1)
06
14
b100 !
b100 +
00
1*
01
1-
1/
b1011 $
b1011 '
#1560000
0B
0)
0(
10
0*
06
04
b101 !
b101 +
1<
0:
11
0-
07
1=
0/
05
1;
b1100 $
b1100 '
#1570000
16
b110 !
b110 +
00
1*
01
1-
1/
b1101 $
b1101 '
#1580000
0B
0(
1<
0:
0)
10
0*
b111 !
b111 +
16
04
11
0-
17
0/
15
b1110 $
b1110 '
#1590000
1B
1(
0<
1:
1)
06
14
b1000 !
b1000 +
00
1*
01
1-
1/
b1111 $
b1111 '
#1600000
0)
16
04
0(
0*
0<
0:
b1010 !
b1010 +
1B
0@
0"
0-
0=
1C
0?
0,
12
0/
05
0;
0A
b1010 #
b1010 &
b0 $
b0 '
#1610000
b1011 !
b1011 +
10
11
1/
b1 $
b1 '
#1620000
1<
00
b1100 !
b1100 +
06
1)
01
07
13
0/
15
b10 $
b10 '
#1630000
b1101 !
b1101 +
10
11
1/
b11 $
b11 '
#1640000
0"
1B
0@
0(
00
16
0)
b1110 !
b1110 +
1<
0:
01
17
03
1=
0/
05
1;
b100 $
b100 '
#1650000
b1111 !
b1111 +
10
11
1/
b101 $
b101 '
#1660000
1"
0B
1@
1(
0<
1:
00
b0 !
b0 +
06
1)
01
07
13
0/
15
b110 $
b110 '
#1670000
b1 !
b1 +
10
11
1/
b111 $
b111 '
#1680000
0(
00
16
0)
0<
0:
b10 !
b10 +
0B
0@
01
17
03
0=
0C
1?
0/
05
0;
1A
b1000 $
b1000 '
#1690000
b11 !
b11 +
10
11
1/
b1001 $
b1001 '
#1700000
1<
00
b100 !
b100 +
06
1)
01
07
13
0/
15
b1010 $
b1010 '
#1710000
b101 !
b101 +
10
11
1/
b1011 $
b1011 '
#1720000
0B
0(
00
16
0)
b110 !
b110 +
1<
0:
01
17
03
1=
0/
05
1;
b1100 $
b1100 '
#1730000
b111 !
b111 +
10
11
1/
b1101 $
b1101 '
#1740000
1B
1(
0<
1:
00
b1000 !
b1000 +
06
1)
01
07
13
0/
15
b1110 $
b1110 '
#1750000
b1001 !
b1001 +
10
11
1/
b1111 $
b1111 '
#1760000
0(
16
0)
0<
0:
b1011 !
b1011 +
1B
0@
0"
17
03
0=
1C
0?
1,
0/
05
0;
0A
b1011 #
b1011 &
b0 $
b0 '
#1770000
1<
1)
06
14
b1100 !
b1100 +
00
1*
01
1-
1/
b1 $
b1 '
#1780000
10
0*
b1101 !
b1101 +
06
04
11
0-
07
13
0/
15
b10 $
b10 '
#1790000
16
b1110 !
b1110 +
00
1*
01
1-
1/
b11 $
b11 '
#1800000
0"
1B
0@
0(
10
0*
16
04
0)
b1111 !
b1111 +
1<
0:
11
0-
17
03
1=
0/
05
1;
b100 $
b100 '
#1810000
1"
0B
1@
1(
0<
1:
1)
06
14
b0 !
b0 +
00
1*
01
1-
1/
b101 $
b101 '
#1820000
10
0*
b1 !
b1 +
06
04
11
0-
07
13
0/
15
b110 $
b110 '
#1830000
16
b10 !
b10 +
00
1*
01
1-
1/
b111 $
b111 '
#1840000
0(
10
0*
16
04
0)
0<
0:
b11 !
b11 +
0B
0@
11
0-
17
03
0=
0C
1?
0/
05
0;
1A
b1000 $
b1000 '
#1850000
1<
1)
06
14
b100 !
b100 +
00
1*
01
1-
1/
b1001 $
b1001 '
#1860000
10
0*
b101 !
b101 +
06
04
11
0-
07
13
0/
15
b1010 $
b1010 '
#1870000
16
b110 !
b110 +
00
1*
01
1-
1/
b1011 $
b1011 '
#1880000
0B
0(
10
0*
16
04
0)
b111 !
b111 +
1<
0:
11
0-
17
03
1=
0/
05
1;
b1100 $
b1100 '
#1890000
1B
1(
0<
1:
1)
06
14
b1000 !
b1000 +
00
1*
01
1-
1/
b1101 $
b1101 '
#1900000
10
0*
b1001 !
b1001 +
06
04
11
0-
07
13
0/
15
b1110 $
b1110 '
#1910000
16
b1010 !
b1010 +
00
1*
01
1-
1/
b1111 $
b1111 '
#1920000
0(
06
1<
0:
0*
0)
b1100 !
b1100 +
1B
0@
0"
0-
03
1C
0?
0,
02
18
0/
05
0;
0A
b1100 #
b1100 &
b0 $
b0 '
#1930000
b1101 !
b1101 +
10
11
1/
b1 $
b1 '
#1940000
00
b1110 !
b1110 +
16
01
17
0/
15
b10 $
b10 '
#1950000
b1111 !
b1111 +
10
11
1/
b11 $
b11 '
#1960000
1"
0B
1@
00
06
b0 !
b0 +
0<
1(
01
07
0=
19
0/
05
1;
b100 $
b100 '
#1970000
b1 !
b1 +
10
11
1/
b101 $
b101 '
#1980000
00
b10 !
b10 +
16
01
17
0/
15
b110 $
b110 '
#1990000
b11 !
b11 +
10
11
1/
b111 $
b111 '
#2000000
00
06
1<
0(
b100 !
b100 +
0B
0@
01
07
1=
09
0C
1?
0/
05
0;
1A
b1000 $
b1000 '
#2010000
b101 !
b101 +
10
11
1/
b1001 $
b1001 '
#2020000
00
b110 !
b110 +
16
01
17
0/
15
b1010 $
b1010 '
#2030000
b111 !
b111 +
10
11
1/
b1011 $
b1011 '
#2040000
1B
00
06
b1000 !
b1000 +
0<
1(
01
07
0=
19
0/
05
1;
b1100 $
b1100 '
#2050000
b1001 !
b1001 +
10
11
1/
b1101 $
b1101 '
#2060000
00
b1010 !
b1010 +
16
01
17
0/
15
b1110 $
b1110 '
#2070000
b1011 !
b1011 +
10
11
1/
b1111 $
b1111 '
#2080000
06
1<
0(
b1101 !
b1101 +
1B
0@
0"
07
1=
09
1C
0?
1,
0/
05
0;
0A
b1101 #
b1101 &
b0 $
b0 '
#2090000
16
b1110 !
b1110 +
00
1*
01
1-
1/
b1 $
b1 '
#2100000
0"
1B
0@
0(
1<
0:
0)
10
0*
b1111 !
b1111 +
16
04
11
0-
17
0/
15
b10 $
b10 '
#2110000
1"
0B
1@
1(
0<
1:
1)
06
14
b0 !
b0 +
00
1*
01
1-
1/
b11 $
b11 '
#2120000
0)
10
0*
06
04
b1 !
b1 +
0<
0:
11
0-
07
0=
19
0/
05
1;
b100 $
b100 '
#2130000
16
b10 !
b10 +
00
1*
01
1-
1/
b101 $
b101 '
#2140000
0<
0)
10
0*
b11 !
b11 +
16
04
11
0-
17
0/
15
b110 $
b110 '
#2150000
1<
1)
06
14
b100 !
b100 +
00
1*
01
1-
1/
b111 $
b111 '
#2160000
0)
10
0*
06
04
1<
0:
0(
b101 !
b101 +
0B
0@
11
0-
07
1=
09
0C
1?
0/
05
0;
1A
b1000 $
b1000 '
#2170000
16
b110 !
b110 +
00
1*
01
1-
1/
b1001 $
b1001 '
#2180000
0B
0(
1<
0:
0)
10
0*
b111 !
b111 +
16
04
11
0-
17
0/
15
b1010 $
b1010 '
#2190000
1B
1(
0<
1:
1)
06
14
b1000 !
b1000 +
00
1*
01
1-
1/
b1011 $
b1011 '
#2200000
0)
10
0*
06
04
b1001 !
b1001 +
0<
0:
11
0-
07
0=
19
0/
05
1;
b1100 $
b1100 '
#2210000
16
b1010 !
b1010 +
00
1*
01
1-
1/
b1101 $
b1101 '
#2220000
0<
0)
10
0*
b1011 !
b1011 +
16
04
11
0-
17
0/
15
b1110 $
b1110 '
#2230000
1<
1)
06
14
b1100 !
b1100 +
00
1*
01
1-
1/
b1111 $
b1111 '
#2240000
0)
16
04
0*
1<
0:
0(
b1110 !
b1110 +
1B
0@
0"
0-
1=
09
1C
0?
0,
12
0/
05
0;
0A
b1110 #
b1110 &
b0 $
b0 '
#2250000
b1111 !
b1111 +
10
11
1/
b1 $
b1 '
#2260000
1"
0B
1@
1(
0<
1:
00
b0 !
b0 +
06
1)
01
07
13
0/
15
b10 $
b10 '
#2270000
b1 !
b1 +
10
11
1/
b11 $
b11 '
#2280000
00
16
0)
b10 !
b10 +
0<
0:
01
17
03
0=
19
0/
05
1;
b100 $
b100 '
#2290000
b11 !
b11 +
10
11
1/
b101 $
b101 '
#2300000
1<
00
b100 !
b100 +
06
1)
01
07
13
0/
15
b110 $
b110 '
#2310000
b101 !
b101 +
10
11
1/
b111 $
b111 '
#2320000
00
16
0)
1<
0:
0(
b110 !
b110 +
0B
0@
01
17
03
1=
09
0C
1?
0/
05
0;
1A
b1000 $
b1000 '
#2330000
b111 !
b111 +
10
11
1/
b1001 $
b1001 '
#2340000
1B
1(
0<
1:
00
b1000 !
b1000 +
06
1)
01
07
13
0/
15
b1010 $
b1010 '
#2350000
b1001 !
b1001 +
10
11
1/
b1011 $
b1011 '
#2360000
00
16
0)
b1010 !
b1010 +
0<
0:
01
17
03
0=
19
0/
05
1;
b1100 $
b1100 '
#2370000
b1011 !
b1011 +
10
11
1/
b1101 $
b1101 '
#2380000
1<
00
b1100 !
b1100 +
06
1)
01
07
13
0/
15
b1110 $
b1110 '
#2390000
b1101 !
b1101 +
10
11
1/
b1111 $
b1111 '
#2400000
16
0)
1<
0:
0(
b1111 !
b1111 +
1B
0@
0"
17
03
1=
09
1C
0?
1,
0/
05
0;
0A
b1111 #
b1111 &
b0 $
b0 '
#2410000
1"
0B
1@
1(
0<
1:
1)
06
14
b0 !
b0 +
00
1*
01
1-
1/
b1 $
b1 '
#2420000
10
0*
b1 !
b1 +
06
04
11
0-
07
13
0/
15
b10 $
b10 '
#2430000
16
b10 !
b10 +
00
1*
01
1-
1/
b11 $
b11 '
#2440000
10
0*
16
04
0)
b11 !
b11 +
0<
0:
11
0-
17
03
0=
19
0/
05
1;
b100 $
b100 '
#2450000
1<
1)
06
14
b100 !
b100 +
00
1*
01
1-
1/
b101 $
b101 '
#2460000
10
0*
b101 !
b101 +
06
04
11
0-
07
13
0/
15
b110 $
b110 '
#2470000
16
b110 !
b110 +
00
1*
01
1-
1/
b111 $
b111 '
#2480000
10
0*
16
04
0)
1<
0:
0(
b111 !
b111 +
0B
0@
11
0-
17
03
1=
09
0C
1?
0/
05
0;
1A
b1000 $
b1000 '
#2490000
1B
1(
0<
1:
1)
06
14
b1000 !
b1000 +
00
1*
01
1-
1/
b1001 $
b1001 '
#2500000
10
0*
b1001 !
b1001 +
06
04
11
0-
07
13
0/
15
b1010 $
b1010 '
